reahl/webdeclarative/__init__.py
reahl/webdeclarative/migrations.py
reahl/webdeclarative/webdeclarative.py
reahl/webdeclarative_dev/__init__.py
reahl/webdeclarative_dev/test_declarativeimplementation.py
reahl_web_declarative-7.0.3.dist-info/LICENSE
reahl_web_declarative-7.0.3.dist-info/METADATA
reahl_web_declarative-7.0.3.dist-info/WHEEL
reahl_web_declarative-7.0.3.dist-info/reahl-component.toml
reahl_web_declarative-7.0.3.dist-info/top_level.txt
reahl_web_declarative-7.0.3.dist-info/RECORD
